persistentidgenerator/__init__.py
persistentidgenerator/seqguidgen.py
persistentidgenerator-1.1.5.dist-info/LICENSE
persistentidgenerator-1.1.5.dist-info/METADATA
persistentidgenerator-1.1.5.dist-info/WHEEL
persistentidgenerator-1.1.5.dist-info/RECORD
