Metadata-Version: 2.1
Name: persistentidgenerator
Version: 1.1.5
Summary: This packages allows creating squential ids for financial entities. It's a fairly simple program that allocates 1 billion ids for each entity.
Home-page: https://github.com/debmishra-daedal/stormwind/persistentidgenerator
License: GNU General Public License v3.0
Keywords: guid,uniqueid,uuid,sequentialid
Author: Deb Mishra
Author-email: email@debmishra.me
Requires-Python: >=3.11,<4.0
Classifier: License :: Other/Proprietary License
Classifier: Programming Language :: Python :: 3
Classifier: Programming Language :: Python :: 3.11
Classifier: Programming Language :: Python :: 3.12
Project-URL: Repository, https://github.com/debmishra-daedal/stormwind
